{
    "os": "Linux-5.15.0-105-generic-x86_64-with-glibc2.17",
    "python": "3.8.16",
    "heartbeatAt": "2024-06-13T20:42:18.539157",
    "startedAt": "2024-06-13T20:42:17.908901",
    "docker": null,
    "cuda": null,
    "args": [],
    "state": "running",
    "program": "main.py",
    "codePath": "LESS/1-WSI_aggregation/main.py",
    "git": {
        "remote": "OPT-GNN",
        "commit": "9e50e5c8356a64c2ebbe770f09a87fe19bebac7c"
    },
    "email": "dengwelong49@gmail.com",
    "root": "/bigdata/projects/beidi/git",
    "host": "tea-3090-2.ece.ubc.ca",
    "username": "tealab",
    "executable": "/data/miniconda3/envs/bdcell/bin/python",
    "cpu_count": 8,
    "cpu_count_logical": 16,
    "cpu_freq": {
        "current": 2400.8926874999997,
        "min": 800.0,
        "max": 5050.0
    },
    "cpu_freq_per_core": [
        {
            "current": 2500.0,
            "min": 800.0,
            "max": 5000.0
        },
        {
            "current": 2500.0,
            "min": 800.0,
            "max": 5000.0
        },
        {
            "current": 2500.0,
            "min": 800.0,
            "max": 5000.0
        },
        {
            "current": 2500.0,
            "min": 800.0,
            "max": 5000.0
        },
        {
            "current": 2500.0,
            "min": 800.0,
            "max": 5200.0
        },
        {
            "current": 2500.0,
            "min": 800.0,
            "max": 5200.0
        },
        {
            "current": 914.283,
            "min": 800.0,
            "max": 5000.0
        },
        {
            "current": 2500.0,
            "min": 800.0,
            "max": 5000.0
        },
        {
            "current": 2500.0,
            "min": 800.0,
            "max": 5000.0
        },
        {
            "current": 2500.0,
            "min": 800.0,
            "max": 5000.0
        },
        {
            "current": 2500.0,
            "min": 800.0,
            "max": 5000.0
        },
        {
            "current": 2500.0,
            "min": 800.0,
            "max": 5000.0
        },
        {
            "current": 2500.0,
            "min": 800.0,
            "max": 5200.0
        },
        {
            "current": 2500.0,
            "min": 800.0,
            "max": 5200.0
        },
        {
            "current": 2500.0,
            "min": 800.0,
            "max": 5000.0
        },
        {
            "current": 2500.0,
            "min": 800.0,
            "max": 5000.0
        }
    ],
    "disk": {
        "total": 76.11578750610352,
        "used": 67.24478530883789
    },
    "gpu": "NVIDIA GeForce RTX 3090",
    "gpu_count": 1,
    "gpu_devices": [
        {
            "name": "NVIDIA GeForce RTX 3090",
            "memory_total": 25769803776
        }
    ],
    "memory": {
        "total": 62.6315803527832
    }
}
